namekox_sqlalchemy/__init__.py
namekox_sqlalchemy/constants.py
namekox_sqlalchemy/exceptions.py
namekox_sqlalchemy/cli/__init__.py
namekox_sqlalchemy/cli/subcmd/__init__.py
namekox_sqlalchemy/cli/subcmd/migration/__init__.py
namekox_sqlalchemy/cli/subcmd/migration/config.py
namekox_sqlalchemy/cli/subcmd/migration/migrate.py
namekox_sqlalchemy/core/__init__.py
namekox_sqlalchemy/core/condition.py
namekox_sqlalchemy/core/shortcuts.py
namekox_sqlalchemy/core/dependencies/__init__.py
namekox_sqlalchemy-0.0.12.dist-info/LICENSE
namekox_sqlalchemy-0.0.12.dist-info/METADATA
namekox_sqlalchemy-0.0.12.dist-info/WHEEL
namekox_sqlalchemy-0.0.12.dist-info/top_level.txt
namekox_sqlalchemy-0.0.12.dist-info/zip-safe
namekox_sqlalchemy-0.0.12.dist-info/RECORD
